bkh_pytorch_utils/__init__.py
bkh_pytorch_utils/mn/__init__.py
bkh_pytorch_utils/mn/utils.py
bkh_pytorch_utils/pl/__init__.py
bkh_pytorch_utils/pl/ddp_helper.py
bkh_pytorch_utils/pl/utils.py
bkh_pytorch_utils/py/__init__.py
bkh_pytorch_utils/py/cm_helper.py
bkh_pytorch_utils/py/mixup.py
bkh_pytorch_utils/py/optim.py
bkh_pytorch_utils/py/utils.py
bkh_pytorch_utils-0.9.15.dist-info/licenses/LICENSE
bkh_pytorch_utils-0.9.15.dist-info/WHEEL
bkh_pytorch_utils-0.9.15.dist-info/METADATA
bkh_pytorch_utils-0.9.15.dist-info/RECORD
